keybard/__init__.py
keybard/center.py
keybard-0.2.0.dist-info/METADATA
keybard-0.2.0.dist-info/WHEEL
keybard-0.2.0.dist-info/top_level.txt
keybard-0.2.0.dist-info/RECORD
