Metadata-Version: 2.1
Name: keybard
Version: 0.2.0
Summary: Librairie Python pour affichage ASCII, son, et mises à jour auto.
Classifier: Programming Language :: Python :: 3
Classifier: License :: OSI Approved :: MIT License
Classifier: Operating System :: OS Independent
Requires-Python: >=3.6
Requires-Dist: pygame >=2.6.0
Requires-Dist: requests >=2.31.0
Requires-Dist: setuptools >=42.0.0
